<?xml version="1.0" encoding="UTF-8"?>
<export version="D">
  <design>
    <source>/home/adam/Projects/iggie/psu/psu.sch</source>
    <date>Sat 17 Aug 2019 19:25:59 BST</date>
    <tool>Eeschema 5.1.4-e60b266~84~ubuntu18.04.1</tool>
    <sheet number="1" name="/" tstamps="/">
      <title_block>
        <title>IGGie PSU</title>
        <company/>
        <rev>1</rev>
        <date>2019-07-22</date>
        <source>psu.sch</source>
        <comment number="1" value="Drawn by: Adam Greig"/>
        <comment number="2" value=""/>
        <comment number="3" value=""/>
        <comment number="4" value=""/>
      </title_block>
    </sheet>
    <sheet number="2" name="/Boost Converter/" tstamps="/6147A5D5/">
      <title_block>
        <title>IGGie PSU: 400V Boost Converter</title>
        <company/>
        <rev>1</rev>
        <date>2019-07-22</date>
        <source>boost_converter.sch</source>
        <comment number="1" value="Drawn by: Adam Greig"/>
        <comment number="2" value=""/>
        <comment number="3" value=""/>
        <comment number="4" value=""/>
      </title_block>
    </sheet>
  </design>
  <components>
    <comp ref="IC4">
      <value>STM32F334K8T6</value>
      <footprint>agg:LQFP-32</footprint>
      <fields>
        <field name="Farnell">2469571</field>
      </fields>
      <libsource lib="agg" part="STM32F3xxKxTx" description="STM32F3 32 pin LQFP package"/>
      <sheetpath names="/" tstamps="/"/>
      <tstamp>5D34A5A9</tstamp>
    </comp>
    <comp ref="J3">
      <value>CTRL</value>
      <footprint>agg:MOLEX-KK-254P-04</footprint>
      <fields>
        <field name="Farnell">1360132</field>
      </fields>
      <libsource lib="agg" part="CONN_01x04" description=""/>
      <sheetpath names="/" tstamps="/"/>
      <tstamp>5D34CC8E</tstamp>
    </comp>
    <comp ref="IC3">
      <value>TSR 1-2450</value>
      <footprint>agg:TSR1</footprint>
      <datasheet>http://www.tracopower.com/products/tsr1.pdf</datasheet>
      <fields>
        <field name="Farnell">1696320</field>
      </fields>
      <libsource lib="agg" part="TSR1" description="TSR1 Switch Mode Regulators"/>
      <sheetpath names="/" tstamps="/"/>
      <tstamp>5D34E326</tstamp>
    </comp>
    <comp ref="IC1">
      <value>ADP3335</value>
      <footprint>agg:MSOP-8</footprint>
      <fields>
        <field name="Farnell">2067775</field>
      </fields>
      <libsource lib="agg" part="ADP3335" description="LDO Voltage Regulator"/>
      <sheetpath names="/" tstamps="/"/>
      <tstamp>5D34F7F2</tstamp>
    </comp>
    <comp ref="P1">
      <value>SWD</value>
      <footprint>agg:FTSH-105-01-L-DV-K</footprint>
      <fields>
        <field name="Farnell">2856437</field>
      </fields>
      <libsource lib="agg" part="SWD" description="Serial Wire Debug Port"/>
      <sheetpath names="/" tstamps="/"/>
      <tstamp>5D35024A</tstamp>
    </comp>
    <comp ref="C6">
      <value>100p</value>
      <footprint>agg:0603</footprint>
      <fields>
        <field name="Farnell">9406115</field>
        <field name="Voltage">50V</field>
      </fields>
      <libsource lib="agg" part="C" description=""/>
      <sheetpath names="/" tstamps="/"/>
      <tstamp>5D35DD08</tstamp>
    </comp>
    <comp ref="C4">
      <value>1µ</value>
      <footprint>agg:0603</footprint>
      <fields>
        <field name="Farnell">2320814</field>
        <field name="Voltage">16V</field>
      </fields>
      <libsource lib="agg" part="C" description=""/>
      <sheetpath names="/" tstamps="/"/>
      <tstamp>5D36009D</tstamp>
    </comp>
    <comp ref="C5">
      <value>1µ</value>
      <footprint>agg:0603</footprint>
      <fields>
        <field name="Farnell">2320814</field>
        <field name="Voltage">16V</field>
      </fields>
      <libsource lib="agg" part="C" description=""/>
      <sheetpath names="/" tstamps="/"/>
      <tstamp>5D361E47</tstamp>
    </comp>
    <comp ref="C3">
      <value>10µ</value>
      <footprint>agg:1210</footprint>
      <fields>
        <field name="Farnell">2781426</field>
        <field name="Voltage">50V</field>
      </fields>
      <libsource lib="agg" part="C" description=""/>
      <sheetpath names="/" tstamps="/"/>
      <tstamp>5D36B937</tstamp>
    </comp>
    <comp ref="L3">
      <value>FB</value>
      <footprint>agg:0603</footprint>
      <fields>
        <field name="Farnell">1515747</field>
      </fields>
      <libsource lib="agg" part="L" description=""/>
      <sheetpath names="/" tstamps="/"/>
      <tstamp>5D480F40</tstamp>
    </comp>
    <comp ref="C12">
      <value>100n</value>
      <footprint>agg:0603</footprint>
      <fields>
        <field name="Farnell">2320803</field>
        <field name="Voltage">50V</field>
      </fields>
      <libsource lib="agg" part="C" description=""/>
      <sheetpath names="/" tstamps="/"/>
      <tstamp>5D492C11</tstamp>
    </comp>
    <comp ref="C10">
      <value>100n</value>
      <footprint>agg:0603</footprint>
      <fields>
        <field name="Farnell">2320803</field>
        <field name="Voltage">50V</field>
      </fields>
      <libsource lib="agg" part="C" description=""/>
      <sheetpath names="/" tstamps="/"/>
      <tstamp>5D4A1E6C</tstamp>
    </comp>
    <comp ref="C9">
      <value>100n</value>
      <footprint>agg:0603</footprint>
      <fields>
        <field name="Farnell">2320803</field>
        <field name="Voltage">50V</field>
      </fields>
      <libsource lib="agg" part="C" description=""/>
      <sheetpath names="/" tstamps="/"/>
      <tstamp>5D4A23E4</tstamp>
    </comp>
    <comp ref="C8">
      <value>10µ</value>
      <footprint>agg:1210</footprint>
      <fields>
        <field name="Farnell">2781426</field>
        <field name="Voltage">50V</field>
      </fields>
      <libsource lib="agg" part="C" description=""/>
      <sheetpath names="/" tstamps="/"/>
      <tstamp>5D4A28AC</tstamp>
    </comp>
    <comp ref="C11">
      <value>1µ</value>
      <footprint>agg:0603</footprint>
      <fields>
        <field name="Farnell">2320814</field>
        <field name="Voltage">16V</field>
      </fields>
      <libsource lib="agg" part="C" description=""/>
      <sheetpath names="/" tstamps="/"/>
      <tstamp>5D4C74FA</tstamp>
    </comp>
    <comp ref="R9">
      <value>1k</value>
      <footprint>agg:0603</footprint>
      <fields>
        <field name="Farnell">2447272</field>
        <field name="Voltage">50V</field>
      </fields>
      <libsource lib="agg" part="R" description=""/>
      <sheetpath names="/" tstamps="/"/>
      <tstamp>5D50B021</tstamp>
    </comp>
    <comp ref="R8">
      <value>1k</value>
      <footprint>agg:0603</footprint>
      <fields>
        <field name="Farnell">2447272</field>
        <field name="Voltage">50V</field>
      </fields>
      <libsource lib="agg" part="R" description=""/>
      <sheetpath names="/" tstamps="/"/>
      <tstamp>5D51D824</tstamp>
    </comp>
    <comp ref="D7">
      <value>ESD_DIODE</value>
      <footprint>agg:0603</footprint>
      <fields>
        <field name="Farnell">2368174</field>
        <field name="Voltage">24V</field>
      </fields>
      <libsource lib="agg" part="ESD_DIODE" description="ESD diode"/>
      <sheetpath names="/" tstamps="/"/>
      <tstamp>5D52E305</tstamp>
    </comp>
    <comp ref="D8">
      <value>ESD_DIODE</value>
      <footprint>agg:0603</footprint>
      <fields>
        <field name="Farnell">2368174</field>
        <field name="Voltage">24V</field>
      </fields>
      <libsource lib="agg" part="ESD_DIODE" description="ESD diode"/>
      <sheetpath names="/" tstamps="/"/>
      <tstamp>5D52F707</tstamp>
    </comp>
    <comp ref="X3">
      <value>M3 MOUNT</value>
      <footprint>agg:M3_MOUNT</footprint>
      <libsource lib="agg" part="PART" description="Generic placeholder part"/>
      <sheetpath names="/" tstamps="/"/>
      <tstamp>5D57DF00</tstamp>
    </comp>
    <comp ref="X4">
      <value>M3 MOUNT</value>
      <footprint>agg:M3_MOUNT</footprint>
      <libsource lib="agg" part="PART" description="Generic placeholder part"/>
      <sheetpath names="/" tstamps="/"/>
      <tstamp>5D582A44</tstamp>
    </comp>
    <comp ref="X2">
      <value>M3 MOUNT</value>
      <footprint>agg:M3_MOUNT</footprint>
      <libsource lib="agg" part="PART" description="Generic placeholder part"/>
      <sheetpath names="/" tstamps="/"/>
      <tstamp>5D582D16</tstamp>
    </comp>
    <comp ref="X1">
      <value>M3 MOUNT</value>
      <footprint>agg:M3_MOUNT</footprint>
      <libsource lib="agg" part="PART" description="Generic placeholder part"/>
      <sheetpath names="/" tstamps="/"/>
      <tstamp>5D582F1C</tstamp>
    </comp>
    <comp ref="Y1">
      <value>25M</value>
      <footprint>agg:XTAL-25x20</footprint>
      <fields>
        <field name="Farnell">2849479</field>
      </fields>
      <libsource lib="agg" part="TCXO_ST" description="4 pin TCXO with Standy"/>
      <sheetpath names="/" tstamps="/"/>
      <tstamp>5D58EA08</tstamp>
    </comp>
    <comp ref="C13">
      <value>100n</value>
      <footprint>agg:0603</footprint>
      <fields>
        <field name="Farnell">2320803</field>
        <field name="Voltage">50V</field>
      </fields>
      <libsource lib="agg" part="C" description=""/>
      <sheetpath names="/" tstamps="/"/>
      <tstamp>5D58FF1C</tstamp>
    </comp>
    <comp ref="X5">
      <value>MAINS PSU</value>
      <datasheet>http://www.farnell.com/datasheets/2547969.pdf</datasheet>
      <fields>
        <field name="Farnell">2815916</field>
      </fields>
      <libsource lib="agg" part="PART" description="Generic placeholder part"/>
      <sheetpath names="/" tstamps="/"/>
      <tstamp>5DF95D2F</tstamp>
    </comp>
    <comp ref="D9">
      <value>ESD_DIODE</value>
      <footprint>agg:0603</footprint>
      <fields>
        <field name="Farnell">2368174</field>
        <field name="Voltage">24V</field>
      </fields>
      <libsource lib="agg" part="ESD_DIODE" description="ESD diode"/>
      <sheetpath names="/" tstamps="/"/>
      <tstamp>5E36EDE7</tstamp>
    </comp>
    <comp ref="D10">
      <value>RED</value>
      <footprint>agg:0603-LED</footprint>
      <fields>
        <field name="Farnell">2290329</field>
      </fields>
      <libsource lib="agg" part="LED" description=""/>
      <sheetpath names="/" tstamps="/"/>
      <tstamp>5E4425BA</tstamp>
    </comp>
    <comp ref="R10">
      <value>1k</value>
      <footprint>agg:0603</footprint>
      <fields>
        <field name="Farnell">2447272</field>
        <field name="Voltage">50V</field>
      </fields>
      <libsource lib="agg" part="R" description=""/>
      <sheetpath names="/" tstamps="/"/>
      <tstamp>5E446932</tstamp>
    </comp>
    <comp ref="R11">
      <value>1k</value>
      <footprint>agg:0603</footprint>
      <fields>
        <field name="Farnell">2447272</field>
        <field name="Voltage">50V</field>
      </fields>
      <libsource lib="agg" part="R" description=""/>
      <sheetpath names="/" tstamps="/"/>
      <tstamp>5E46FDF7</tstamp>
    </comp>
    <comp ref="D11">
      <value>GRN</value>
      <footprint>agg:0603-LED</footprint>
      <fields>
        <field name="Farnell">2290328</field>
      </fields>
      <libsource lib="agg" part="LED" description=""/>
      <sheetpath names="/" tstamps="/"/>
      <tstamp>5E4706BF</tstamp>
    </comp>
    <comp ref="D4">
      <value>GRN</value>
      <footprint>agg:0603-LED</footprint>
      <fields>
        <field name="Farnell">2290328</field>
      </fields>
      <libsource lib="agg" part="LED" description=""/>
      <sheetpath names="/" tstamps="/"/>
      <tstamp>5E4B8DC2</tstamp>
    </comp>
    <comp ref="R4">
      <value>1k</value>
      <footprint>agg:0603</footprint>
      <fields>
        <field name="Farnell">2447272</field>
        <field name="Voltage">50V</field>
      </fields>
      <libsource lib="agg" part="R" description=""/>
      <sheetpath names="/" tstamps="/"/>
      <tstamp>5E4B8DCC</tstamp>
    </comp>
    <comp ref="D5">
      <value>GRN</value>
      <footprint>agg:0603-LED</footprint>
      <fields>
        <field name="Farnell">2290328</field>
      </fields>
      <libsource lib="agg" part="LED" description=""/>
      <sheetpath names="/" tstamps="/"/>
      <tstamp>5E4D4C24</tstamp>
    </comp>
    <comp ref="R5">
      <value>1k</value>
      <footprint>agg:0603</footprint>
      <fields>
        <field name="Farnell">2447272</field>
        <field name="Voltage">50V</field>
      </fields>
      <libsource lib="agg" part="R" description=""/>
      <sheetpath names="/" tstamps="/"/>
      <tstamp>5E4D4C2E</tstamp>
    </comp>
    <comp ref="D12">
      <value>GRN</value>
      <footprint>agg:0603-LED</footprint>
      <fields>
        <field name="Farnell">2290328</field>
      </fields>
      <libsource lib="agg" part="LED" description=""/>
      <sheetpath names="/" tstamps="/"/>
      <tstamp>5E567628</tstamp>
    </comp>
    <comp ref="R12">
      <value>1k</value>
      <footprint>agg:0603</footprint>
      <fields>
        <field name="Farnell">2447272</field>
        <field name="Voltage">50V</field>
      </fields>
      <libsource lib="agg" part="R" description=""/>
      <sheetpath names="/" tstamps="/"/>
      <tstamp>5E5678D6</tstamp>
    </comp>
    <comp ref="D13">
      <value>GRN</value>
      <footprint>agg:0603-LED</footprint>
      <fields>
        <field name="Farnell">2290328</field>
      </fields>
      <libsource lib="agg" part="LED" description=""/>
      <sheetpath names="/" tstamps="/"/>
      <tstamp>5E5FA61D</tstamp>
    </comp>
    <comp ref="R13">
      <value>1k</value>
      <footprint>agg:0603</footprint>
      <fields>
        <field name="Farnell">2447272</field>
        <field name="Voltage">50V</field>
      </fields>
      <libsource lib="agg" part="R" description=""/>
      <sheetpath names="/" tstamps="/"/>
      <tstamp>5E5FA627</tstamp>
    </comp>
    <comp ref="R7">
      <value>10k</value>
      <footprint>agg:0603</footprint>
      <fields>
        <field name="Farnell">2447230</field>
        <field name="Voltage">50V</field>
      </fields>
      <libsource lib="agg" part="R" description=""/>
      <sheetpath names="/" tstamps="/"/>
      <tstamp>5E824714</tstamp>
    </comp>
    <comp ref="D1">
      <value>VSSC520S-M3/9AT</value>
      <footprint>aggl:DO-214AB-SMC</footprint>
      <datasheet>http://www.farnell.com/datasheets/2050375.pdf</datasheet>
      <fields>
        <field name="Farnell">1859669</field>
      </fields>
      <libsource lib="agg" part="SCHOTTKY" description="Schottky Diode"/>
      <sheetpath names="/" tstamps="/"/>
      <tstamp>5EF19544</tstamp>
    </comp>
    <comp ref="D2">
      <value>SMAJ58A</value>
      <footprint>agg:DO-214AC-SMA</footprint>
      <datasheet>http://www.farnell.com/datasheets/2076055.pdf</datasheet>
      <fields>
        <field name="Farnell">1899460</field>
      </fields>
      <libsource lib="agg" part="SCHOTTKY" description="Schottky Diode"/>
      <sheetpath names="/" tstamps="/"/>
      <tstamp>5F25B43C</tstamp>
    </comp>
    <comp ref="IC2">
      <value>TSR 1-24150</value>
      <footprint>agg:TSR1</footprint>
      <datasheet>http://www.tracopower.com/products/tsr1.pdf</datasheet>
      <fields>
        <field name="Farnell">1672131</field>
      </fields>
      <libsource lib="agg" part="TSR1" description="TSR1 Switch Mode Regulators"/>
      <sheetpath names="/" tstamps="/"/>
      <tstamp>5F620D86</tstamp>
    </comp>
    <comp ref="C2">
      <value>10µ</value>
      <footprint>agg:1210</footprint>
      <fields>
        <field name="Farnell">2781426</field>
        <field name="Voltage">50V</field>
      </fields>
      <libsource lib="agg" part="C" description=""/>
      <sheetpath names="/" tstamps="/"/>
      <tstamp>5F76EEF3</tstamp>
    </comp>
    <comp ref="R3">
      <value>10k</value>
      <footprint>agg:0603</footprint>
      <fields>
        <field name="Farnell">2447230</field>
        <field name="Voltage">50V</field>
      </fields>
      <libsource lib="agg" part="R" description=""/>
      <sheetpath names="/" tstamps="/"/>
      <tstamp>5F7983C7</tstamp>
    </comp>
    <comp ref="D3">
      <value>GRN</value>
      <footprint>agg:0603-LED</footprint>
      <fields>
        <field name="Farnell">2290328</field>
      </fields>
      <libsource lib="agg" part="LED" description=""/>
      <sheetpath names="/" tstamps="/"/>
      <tstamp>5F7983BD</tstamp>
    </comp>
    <comp ref="R6">
      <value>10k</value>
      <footprint>agg:0603</footprint>
      <fields>
        <field name="Farnell">2447230</field>
        <field name="Voltage">50V</field>
      </fields>
      <libsource lib="agg" part="R" description=""/>
      <sheetpath names="/" tstamps="/"/>
      <tstamp>5E476386</tstamp>
    </comp>
    <comp ref="D6">
      <value>GRN</value>
      <footprint>agg:0603-LED</footprint>
      <fields>
        <field name="Farnell">2290328</field>
      </fields>
      <libsource lib="agg" part="LED" description=""/>
      <sheetpath names="/" tstamps="/"/>
      <tstamp>5E474640</tstamp>
    </comp>
    <comp ref="J1">
      <value>HV_OUT</value>
      <footprint>agg:MOLEX-KK-254P-03</footprint>
      <fields>
        <field name="Farnell">1360131</field>
      </fields>
      <libsource lib="agg" part="CONN_01x03" description=""/>
      <sheetpath names="/" tstamps="/"/>
      <tstamp>61502606</tstamp>
    </comp>
    <comp ref="R1">
      <value>100k</value>
      <footprint>agg:0603</footprint>
      <fields>
        <field name="Farnell">2447226</field>
        <field name="Voltage">50V</field>
      </fields>
      <libsource lib="agg" part="R" description=""/>
      <sheetpath names="/" tstamps="/"/>
      <tstamp>61EA5AD4</tstamp>
    </comp>
    <comp ref="R2">
      <value>10k</value>
      <footprint>agg:0603</footprint>
      <fields>
        <field name="Farnell">2447230</field>
        <field name="Voltage">50V</field>
      </fields>
      <libsource lib="agg" part="R" description=""/>
      <sheetpath names="/" tstamps="/"/>
      <tstamp>61EA5ADA</tstamp>
    </comp>
    <comp ref="C7">
      <value>100p</value>
      <footprint>agg:0603</footprint>
      <fields>
        <field name="Farnell">9406115</field>
        <field name="Voltage">50V</field>
      </fields>
      <libsource lib="agg" part="C" description=""/>
      <sheetpath names="/" tstamps="/"/>
      <tstamp>61EA5AF4</tstamp>
    </comp>
    <comp ref="C1">
      <value>100µ</value>
      <footprint>agg:PANASONIC-SMDCAP-G</footprint>
      <datasheet>http://industrial.panasonic.com/cdbs/www-data/pdf/RDE0000/ABA0000C1187.pdf</datasheet>
      <fields>
        <field name="Farnell">2079271</field>
        <field name="Voltage">50V</field>
      </fields>
      <libsource lib="agg" part="CP" description="Polarised Capacitor"/>
      <sheetpath names="/" tstamps="/"/>
      <tstamp>62DF485C</tstamp>
    </comp>
    <comp ref="J2">
      <value>PWR_IN</value>
      <footprint>agg:BARRELJACK</footprint>
      <libsource lib="agg" part="BarrelJack" description=""/>
      <sheetpath names="/" tstamps="/"/>
      <tstamp>5D609896</tstamp>
    </comp>
    <comp ref="TP2">
      <value>TESTPAD</value>
      <footprint>agg:SIL-254P-01</footprint>
      <libsource lib="agg" part="TESTPAD" description="Test pad"/>
      <sheetpath names="/" tstamps="/"/>
      <tstamp>5D6C093C</tstamp>
    </comp>
    <comp ref="TP1">
      <value>TESTPAD</value>
      <footprint>agg:TESTPAD</footprint>
      <libsource lib="agg" part="TESTPAD" description="Test pad"/>
      <sheetpath names="/" tstamps="/"/>
      <tstamp>5D6D1532</tstamp>
    </comp>
    <comp ref="TP3">
      <value>TESTPAD</value>
      <footprint>agg:TESTPAD</footprint>
      <libsource lib="agg" part="TESTPAD" description="Test pad"/>
      <sheetpath names="/" tstamps="/"/>
      <tstamp>5D6DEA1E</tstamp>
    </comp>
    <comp ref="TP4">
      <value>TESTPAD</value>
      <footprint>agg:TESTPAD</footprint>
      <libsource lib="agg" part="TESTPAD" description="Test pad"/>
      <sheetpath names="/" tstamps="/"/>
      <tstamp>5D6EBB60</tstamp>
    </comp>
    <comp ref="TP5">
      <value>TESTPAD</value>
      <footprint>agg:TESTPAD</footprint>
      <libsource lib="agg" part="TESTPAD" description="Test pad"/>
      <sheetpath names="/" tstamps="/"/>
      <tstamp>5D6F9179</tstamp>
    </comp>
    <comp ref="IC6">
      <value>MCP1416</value>
      <footprint>agg:SOT-23-5</footprint>
      <datasheet>http://ww1.microchip.com/downloads/en/DeviceDoc/20002092F.pdf</datasheet>
      <fields>
        <field name="Farnell">1630421</field>
      </fields>
      <libsource lib="agg" part="MCP1416" description="1.5A High Speed Power MOSFET Driver"/>
      <sheetpath names="/Boost Converter/" tstamps="/6147A5D5/"/>
      <tstamp>614C600D</tstamp>
    </comp>
    <comp ref="C30">
      <value>1µ</value>
      <footprint>agg:1206</footprint>
      <fields>
        <field name="Farnell">1759454</field>
        <field name="Voltage">50V</field>
      </fields>
      <libsource lib="agg" part="C" description=""/>
      <sheetpath names="/Boost Converter/" tstamps="/6147A5D5/"/>
      <tstamp>614C6028</tstamp>
    </comp>
    <comp ref="C31">
      <value>100n</value>
      <footprint>agg:0603</footprint>
      <fields>
        <field name="Farnell">2320803</field>
        <field name="Voltage">50V</field>
      </fields>
      <libsource lib="agg" part="C" description=""/>
      <sheetpath names="/Boost Converter/" tstamps="/6147A5D5/"/>
      <tstamp>614C6037</tstamp>
    </comp>
    <comp ref="IC7">
      <value>MCP1416</value>
      <footprint>agg:SOT-23-5</footprint>
      <datasheet>http://ww1.microchip.com/downloads/en/DeviceDoc/20002092F.pdf</datasheet>
      <fields>
        <field name="Farnell">1630421</field>
      </fields>
      <libsource lib="agg" part="MCP1416" description="1.5A High Speed Power MOSFET Driver"/>
      <sheetpath names="/Boost Converter/" tstamps="/6147A5D5/"/>
      <tstamp>614C6048</tstamp>
    </comp>
    <comp ref="C32">
      <value>1µ</value>
      <footprint>agg:1206</footprint>
      <fields>
        <field name="Farnell">1759454</field>
        <field name="Voltage">50V</field>
      </fields>
      <libsource lib="agg" part="C" description=""/>
      <sheetpath names="/Boost Converter/" tstamps="/6147A5D5/"/>
      <tstamp>614C6059</tstamp>
    </comp>
    <comp ref="C33">
      <value>100n</value>
      <footprint>agg:0603</footprint>
      <fields>
        <field name="Farnell">2320803</field>
        <field name="Voltage">50V</field>
      </fields>
      <libsource lib="agg" part="C" description=""/>
      <sheetpath names="/Boost Converter/" tstamps="/6147A5D5/"/>
      <tstamp>614C6068</tstamp>
    </comp>
    <comp ref="R33">
      <value>100k</value>
      <footprint>agg:0603</footprint>
      <fields>
        <field name="Farnell">2447226</field>
        <field name="Voltage">50V</field>
      </fields>
      <libsource lib="agg" part="R" description=""/>
      <sheetpath names="/Boost Converter/" tstamps="/6147A5D5/"/>
      <tstamp>614C607E</tstamp>
    </comp>
    <comp ref="R35">
      <value>100k</value>
      <footprint>agg:0603</footprint>
      <fields>
        <field name="Farnell">2447226</field>
        <field name="Voltage">50V</field>
      </fields>
      <libsource lib="agg" part="R" description=""/>
      <sheetpath names="/Boost Converter/" tstamps="/6147A5D5/"/>
      <tstamp>614C608E</tstamp>
    </comp>
    <comp ref="R36">
      <value>10m</value>
      <footprint>agg:1206</footprint>
      <fields>
        <field name="Farnell">2079442</field>
      </fields>
      <libsource lib="agg" part="R" description=""/>
      <sheetpath names="/Boost Converter/" tstamps="/6147A5D5/"/>
      <tstamp>614C60A6</tstamp>
    </comp>
    <comp ref="R31">
      <value>1k</value>
      <footprint>agg:0603</footprint>
      <fields>
        <field name="Farnell">2447272</field>
        <field name="Voltage">50V</field>
      </fields>
      <libsource lib="agg" part="R" description=""/>
      <sheetpath names="/Boost Converter/" tstamps="/6147A5D5/"/>
      <tstamp>614C60C2</tstamp>
    </comp>
    <comp ref="TP12">
      <value>TESTPAD</value>
      <footprint>agg:TESTPAD</footprint>
      <libsource lib="agg" part="TESTPAD" description="Test pad"/>
      <sheetpath names="/Boost Converter/" tstamps="/6147A5D5/"/>
      <tstamp>614C60CA</tstamp>
    </comp>
    <comp ref="R34">
      <value>10m</value>
      <footprint>agg:1206</footprint>
      <fields>
        <field name="Farnell">2079442</field>
      </fields>
      <libsource lib="agg" part="R" description=""/>
      <sheetpath names="/Boost Converter/" tstamps="/6147A5D5/"/>
      <tstamp>614C60D3</tstamp>
    </comp>
    <comp ref="R30">
      <value>1k</value>
      <footprint>agg:0603</footprint>
      <fields>
        <field name="Farnell">2447272</field>
        <field name="Voltage">50V</field>
      </fields>
      <libsource lib="agg" part="R" description=""/>
      <sheetpath names="/Boost Converter/" tstamps="/6147A5D5/"/>
      <tstamp>614C60EF</tstamp>
    </comp>
    <comp ref="TP8">
      <value>TESTPAD</value>
      <footprint>agg:TESTPAD</footprint>
      <libsource lib="agg" part="TESTPAD" description="Test pad"/>
      <sheetpath names="/Boost Converter/" tstamps="/6147A5D5/"/>
      <tstamp>614C60FA</tstamp>
    </comp>
    <comp ref="C27">
      <value>100p</value>
      <footprint>agg:0603</footprint>
      <fields>
        <field name="Farnell">9406115</field>
        <field name="Voltage">50V</field>
      </fields>
      <libsource lib="agg" part="C" description=""/>
      <sheetpath names="/Boost Converter/" tstamps="/6147A5D5/"/>
      <tstamp>614C6101</tstamp>
    </comp>
    <comp ref="C28">
      <value>100p</value>
      <footprint>agg:0603</footprint>
      <fields>
        <field name="Farnell">9406115</field>
        <field name="Voltage">50V</field>
      </fields>
      <libsource lib="agg" part="C" description=""/>
      <sheetpath names="/Boost Converter/" tstamps="/6147A5D5/"/>
      <tstamp>614C6112</tstamp>
    </comp>
    <comp ref="C18">
      <value>1µ</value>
      <footprint>agg:1206</footprint>
      <fields>
        <field name="Farnell">1759454</field>
        <field name="Voltage">50V</field>
      </fields>
      <libsource lib="agg" part="C" description=""/>
      <sheetpath names="/Boost Converter/" tstamps="/6147A5D5/"/>
      <tstamp>614C612C</tstamp>
    </comp>
    <comp ref="L1">
      <value>47µH</value>
      <footprint>agg:MSS1210</footprint>
      <datasheet>http://www.farnell.com/datasheets/1681953.pdf</datasheet>
      <fields>
        <field name="Farnell">2288335</field>
      </fields>
      <libsource lib="agg" part="L" description=""/>
      <sheetpath names="/Boost Converter/" tstamps="/6147A5D5/"/>
      <tstamp>614C6132</tstamp>
    </comp>
    <comp ref="C22">
      <value>68µ</value>
      <footprint>agg:PANASONIC-SMDCAP-K</footprint>
      <datasheet>http://industrial.panasonic.com/cdbs/www-data/pdf/RDE0000/ABA0000C1202.pdf</datasheet>
      <fields>
        <field name="Farnell">2326343</field>
        <field name="Voltage">250V</field>
      </fields>
      <libsource lib="agg" part="CP" description="Polarised Capacitor"/>
      <sheetpath names="/Boost Converter/" tstamps="/6147A5D5/"/>
      <tstamp>614C6139</tstamp>
    </comp>
    <comp ref="D14">
      <value>STTH512B</value>
      <footprint>agg:DPAK_DIODE</footprint>
      <datasheet>https://www.st.com/resource/en/datasheet/stth512.pdf</datasheet>
      <fields>
        <field name="Farnell">2344055</field>
      </fields>
      <libsource lib="agg" part="SCHOTTKY" description="Schottky Diode"/>
      <sheetpath names="/Boost Converter/" tstamps="/6147A5D5/"/>
      <tstamp>614C615C</tstamp>
    </comp>
    <comp ref="C19">
      <value>1µ</value>
      <footprint>agg:2220</footprint>
      <datasheet>http://www.farnell.com/datasheets/2048632.pdf</datasheet>
      <fields>
        <field name="Farnell">1828845</field>
        <field name="Voltage">250V</field>
      </fields>
      <libsource lib="agg" part="C" description=""/>
      <sheetpath names="/Boost Converter/" tstamps="/6147A5D5/"/>
      <tstamp>614C6163</tstamp>
    </comp>
    <comp ref="R14">
      <value>DNF</value>
      <footprint>agg:0805</footprint>
      <libsource lib="agg" part="R" description=""/>
      <sheetpath names="/Boost Converter/" tstamps="/6147A5D5/"/>
      <tstamp>614C61BB</tstamp>
    </comp>
    <comp ref="C14">
      <value>DNF</value>
      <footprint>agg:0805</footprint>
      <fields>
        <field name="Voltage">250V</field>
      </fields>
      <libsource lib="agg" part="C" description=""/>
      <sheetpath names="/Boost Converter/" tstamps="/6147A5D5/"/>
      <tstamp>614C61C2</tstamp>
    </comp>
    <comp ref="R17">
      <value>DNF</value>
      <footprint>agg:0805</footprint>
      <libsource lib="agg" part="R" description=""/>
      <sheetpath names="/Boost Converter/" tstamps="/6147A5D5/"/>
      <tstamp>614C61E4</tstamp>
    </comp>
    <comp ref="C17">
      <value>DNF</value>
      <footprint>agg:0805</footprint>
      <fields>
        <field name="Voltage">250V</field>
      </fields>
      <libsource lib="agg" part="C" description=""/>
      <sheetpath names="/Boost Converter/" tstamps="/6147A5D5/"/>
      <tstamp>614C61F7</tstamp>
    </comp>
    <comp ref="C16">
      <value>DNF</value>
      <footprint>agg:0805</footprint>
      <fields>
        <field name="Voltage">250V</field>
      </fields>
      <libsource lib="agg" part="C" description=""/>
      <sheetpath names="/Boost Converter/" tstamps="/6147A5D5/"/>
      <tstamp>614C61FE</tstamp>
    </comp>
    <comp ref="R16">
      <value>DNF</value>
      <footprint>agg:0805</footprint>
      <libsource lib="agg" part="R" description=""/>
      <sheetpath names="/Boost Converter/" tstamps="/6147A5D5/"/>
      <tstamp>614C6204</tstamp>
    </comp>
    <comp ref="R21">
      <value>100k</value>
      <footprint>agg:1206</footprint>
      <fields>
        <field name="Farnell">2447453</field>
        <field name="Voltage">200V</field>
      </fields>
      <libsource lib="agg" part="R" description=""/>
      <sheetpath names="/Boost Converter/" tstamps="/6147A5D5/"/>
      <tstamp>614C6211</tstamp>
    </comp>
    <comp ref="R24">
      <value>100k</value>
      <footprint>agg:1206</footprint>
      <fields>
        <field name="Farnell">2447453</field>
        <field name="Voltage">200V</field>
      </fields>
      <libsource lib="agg" part="R" description=""/>
      <sheetpath names="/Boost Converter/" tstamps="/6147A5D5/"/>
      <tstamp>614C6217</tstamp>
    </comp>
    <comp ref="R22">
      <value>10k</value>
      <footprint>agg:0603</footprint>
      <fields>
        <field name="Farnell">2447230</field>
        <field name="Voltage">50V</field>
      </fields>
      <libsource lib="agg" part="R" description=""/>
      <sheetpath names="/Boost Converter/" tstamps="/6147A5D5/"/>
      <tstamp>614C624B</tstamp>
    </comp>
    <comp ref="IC8">
      <value>MCP1416</value>
      <footprint>agg:SOT-23-5</footprint>
      <datasheet>http://ww1.microchip.com/downloads/en/DeviceDoc/20002092F.pdf</datasheet>
      <fields>
        <field name="Farnell">1630421</field>
      </fields>
      <libsource lib="agg" part="MCP1416" description="1.5A High Speed Power MOSFET Driver"/>
      <sheetpath names="/Boost Converter/" tstamps="/6147A5D5/"/>
      <tstamp>614C6285</tstamp>
    </comp>
    <comp ref="R40">
      <value>100k</value>
      <footprint>agg:0603</footprint>
      <fields>
        <field name="Farnell">2447226</field>
        <field name="Voltage">50V</field>
      </fields>
      <libsource lib="agg" part="R" description=""/>
      <sheetpath names="/Boost Converter/" tstamps="/6147A5D5/"/>
      <tstamp>614C6291</tstamp>
    </comp>
    <comp ref="C34">
      <value>1µ</value>
      <footprint>agg:1206</footprint>
      <fields>
        <field name="Farnell">1759454</field>
        <field name="Voltage">50V</field>
      </fields>
      <libsource lib="agg" part="C" description=""/>
      <sheetpath names="/Boost Converter/" tstamps="/6147A5D5/"/>
      <tstamp>614C62C8</tstamp>
    </comp>
    <comp ref="C35">
      <value>100n</value>
      <footprint>agg:0603</footprint>
      <fields>
        <field name="Farnell">2320803</field>
        <field name="Voltage">50V</field>
      </fields>
      <libsource lib="agg" part="C" description=""/>
      <sheetpath names="/Boost Converter/" tstamps="/6147A5D5/"/>
      <tstamp>614C62D7</tstamp>
    </comp>
    <comp ref="R39">
      <value>10m</value>
      <footprint>agg:1206</footprint>
      <fields>
        <field name="Farnell">2079442</field>
      </fields>
      <libsource lib="agg" part="R" description=""/>
      <sheetpath names="/Boost Converter/" tstamps="/6147A5D5/"/>
      <tstamp>614C6308</tstamp>
    </comp>
    <comp ref="R18">
      <value>10m</value>
      <footprint>agg:1206</footprint>
      <fields>
        <field name="Farnell">2079442</field>
      </fields>
      <libsource lib="agg" part="R" description=""/>
      <sheetpath names="/Boost Converter/" tstamps="/6147A5D5/"/>
      <tstamp>614C6315</tstamp>
    </comp>
    <comp ref="R45">
      <value>1k</value>
      <footprint>agg:0603</footprint>
      <fields>
        <field name="Farnell">2447272</field>
        <field name="Voltage">50V</field>
      </fields>
      <libsource lib="agg" part="R" description=""/>
      <sheetpath names="/Boost Converter/" tstamps="/6147A5D5/"/>
      <tstamp>615465BF</tstamp>
    </comp>
    <comp ref="R41">
      <value>68k</value>
      <footprint>agg:0603</footprint>
      <fields>
        <field name="Farnell">2447420</field>
        <field name="Voltage">50V</field>
      </fields>
      <libsource lib="agg" part="R" description=""/>
      <sheetpath names="/Boost Converter/" tstamps="/6147A5D5/"/>
      <tstamp>615465C5</tstamp>
    </comp>
    <comp ref="C42">
      <value>100p</value>
      <footprint>agg:0603</footprint>
      <fields>
        <field name="Farnell">9406115</field>
        <field name="Voltage">50V</field>
      </fields>
      <libsource lib="agg" part="C" description=""/>
      <sheetpath names="/Boost Converter/" tstamps="/6147A5D5/"/>
      <tstamp>615465CB</tstamp>
    </comp>
    <comp ref="R46">
      <value>1k</value>
      <footprint>agg:0603</footprint>
      <fields>
        <field name="Farnell">2447272</field>
        <field name="Voltage">50V</field>
      </fields>
      <libsource lib="agg" part="R" description=""/>
      <sheetpath names="/Boost Converter/" tstamps="/6147A5D5/"/>
      <tstamp>615465FA</tstamp>
    </comp>
    <comp ref="R42">
      <value>68k</value>
      <footprint>agg:0603</footprint>
      <fields>
        <field name="Farnell">2447420</field>
        <field name="Voltage">50V</field>
      </fields>
      <libsource lib="agg" part="R" description=""/>
      <sheetpath names="/Boost Converter/" tstamps="/6147A5D5/"/>
      <tstamp>61546600</tstamp>
    </comp>
    <comp ref="C43">
      <value>100p</value>
      <footprint>agg:0603</footprint>
      <fields>
        <field name="Farnell">9406115</field>
        <field name="Voltage">50V</field>
      </fields>
      <libsource lib="agg" part="C" description=""/>
      <sheetpath names="/Boost Converter/" tstamps="/6147A5D5/"/>
      <tstamp>61546606</tstamp>
    </comp>
    <comp ref="R47">
      <value>1k</value>
      <footprint>agg:0603</footprint>
      <fields>
        <field name="Farnell">2447272</field>
        <field name="Voltage">50V</field>
      </fields>
      <libsource lib="agg" part="R" description=""/>
      <sheetpath names="/Boost Converter/" tstamps="/6147A5D5/"/>
      <tstamp>61546644</tstamp>
    </comp>
    <comp ref="R43">
      <value>1M</value>
      <footprint>agg:0603</footprint>
      <fields>
        <field name="Farnell">2447285</field>
        <field name="Voltage">50V</field>
      </fields>
      <libsource lib="agg" part="R" description=""/>
      <sheetpath names="/Boost Converter/" tstamps="/6147A5D5/"/>
      <tstamp>6154664A</tstamp>
    </comp>
    <comp ref="C44">
      <value>100p</value>
      <footprint>agg:0603</footprint>
      <fields>
        <field name="Farnell">9406115</field>
        <field name="Voltage">50V</field>
      </fields>
      <libsource lib="agg" part="C" description=""/>
      <sheetpath names="/Boost Converter/" tstamps="/6147A5D5/"/>
      <tstamp>61546650</tstamp>
    </comp>
    <comp ref="IC12">
      <value>AD8551</value>
      <footprint>agg:MSOP-8</footprint>
      <datasheet>https://www.analog.com/media/en/technical-documentation/data-sheets/AD8551_8552_8554.pdf</datasheet>
      <fields>
        <field name="Farnell">2460985</field>
      </fields>
      <libsource lib="agg" part="AD8551" description="Zero-Drift, Single-Supply, Rail-to-Rail Input/Output Operational Amplifiers"/>
      <sheetpath names="/Boost Converter/" tstamps="/6147A5D5/"/>
      <tstamp>61546678</tstamp>
    </comp>
    <comp ref="IC9">
      <value>INA139</value>
      <footprint>agg:SOT-23-5</footprint>
      <datasheet>http://www.ti.com/lit/ds/symlink/ina139.pdf</datasheet>
      <fields>
        <field name="Farnell">1470398</field>
      </fields>
      <libsource lib="agg" part="INA139" description="High-Side Measurement Current Shunt Monitor"/>
      <sheetpath names="/Boost Converter/" tstamps="/6147A5D5/"/>
      <tstamp>6154667F</tstamp>
    </comp>
    <comp ref="R48">
      <value>100k</value>
      <footprint>agg:0603</footprint>
      <fields>
        <field name="Farnell">2447226</field>
        <field name="Voltage">50V</field>
      </fields>
      <libsource lib="agg" part="R" description=""/>
      <sheetpath names="/Boost Converter/" tstamps="/6147A5D5/"/>
      <tstamp>6154668E</tstamp>
    </comp>
    <comp ref="C36">
      <value>100n</value>
      <footprint>agg:0603</footprint>
      <fields>
        <field name="Farnell">2320803</field>
        <field name="Voltage">50V</field>
      </fields>
      <libsource lib="agg" part="C" description=""/>
      <sheetpath names="/Boost Converter/" tstamps="/6147A5D5/"/>
      <tstamp>615466AC</tstamp>
    </comp>
    <comp ref="C37">
      <value>1µ</value>
      <footprint>agg:0603</footprint>
      <fields>
        <field name="Farnell">2320814</field>
        <field name="Voltage">16V</field>
      </fields>
      <libsource lib="agg" part="C" description=""/>
      <sheetpath names="/Boost Converter/" tstamps="/6147A5D5/"/>
      <tstamp>615466B3</tstamp>
    </comp>
    <comp ref="C40">
      <value>100n</value>
      <footprint>agg:0603</footprint>
      <fields>
        <field name="Farnell">2320803</field>
        <field name="Voltage">50V</field>
      </fields>
      <libsource lib="agg" part="C" description=""/>
      <sheetpath names="/Boost Converter/" tstamps="/6147A5D5/"/>
      <tstamp>615466D6</tstamp>
    </comp>
    <comp ref="C45">
      <value>100n</value>
      <footprint>agg:0603</footprint>
      <fields>
        <field name="Farnell">2320803</field>
        <field name="Voltage">50V</field>
      </fields>
      <libsource lib="agg" part="C" description=""/>
      <sheetpath names="/Boost Converter/" tstamps="/6147A5D5/"/>
      <tstamp>615466EB</tstamp>
    </comp>
    <comp ref="C41">
      <value>1µ</value>
      <footprint>agg:0603</footprint>
      <fields>
        <field name="Farnell">2320814</field>
        <field name="Voltage">16V</field>
      </fields>
      <libsource lib="agg" part="C" description=""/>
      <sheetpath names="/Boost Converter/" tstamps="/6147A5D5/"/>
      <tstamp>61546700</tstamp>
    </comp>
    <comp ref="C46">
      <value>1µ</value>
      <footprint>agg:0603</footprint>
      <fields>
        <field name="Farnell">2320814</field>
        <field name="Voltage">16V</field>
      </fields>
      <libsource lib="agg" part="C" description=""/>
      <sheetpath names="/Boost Converter/" tstamps="/6147A5D5/"/>
      <tstamp>61546715</tstamp>
    </comp>
    <comp ref="C47">
      <value>100n</value>
      <footprint>agg:0603</footprint>
      <fields>
        <field name="Farnell">2320803</field>
        <field name="Voltage">50V</field>
      </fields>
      <libsource lib="agg" part="C" description=""/>
      <sheetpath names="/Boost Converter/" tstamps="/6147A5D5/"/>
      <tstamp>6154672A</tstamp>
    </comp>
    <comp ref="R20">
      <value>499k</value>
      <footprint>agg:0805</footprint>
      <fields>
        <field name="Farnell">2447667</field>
        <field name="Voltage">150V</field>
      </fields>
      <libsource lib="agg" part="R" description=""/>
      <sheetpath names="/Boost Converter/" tstamps="/6147A5D5/"/>
      <tstamp>6158B23C</tstamp>
    </comp>
    <comp ref="R23">
      <value>499k</value>
      <footprint>agg:0805</footprint>
      <fields>
        <field name="Farnell">2447667</field>
        <field name="Voltage">150V</field>
      </fields>
      <libsource lib="agg" part="R" description=""/>
      <sheetpath names="/Boost Converter/" tstamps="/6147A5D5/"/>
      <tstamp>6158B242</tstamp>
    </comp>
    <comp ref="R26">
      <value>499k</value>
      <footprint>agg:0805</footprint>
      <fields>
        <field name="Farnell">2447667</field>
        <field name="Voltage">150V</field>
      </fields>
      <libsource lib="agg" part="R" description=""/>
      <sheetpath names="/Boost Converter/" tstamps="/6147A5D5/"/>
      <tstamp>6158B248</tstamp>
    </comp>
    <comp ref="R28">
      <value>499k</value>
      <footprint>agg:0805</footprint>
      <fields>
        <field name="Farnell">2447667</field>
        <field name="Voltage">150V</field>
      </fields>
      <libsource lib="agg" part="R" description=""/>
      <sheetpath names="/Boost Converter/" tstamps="/6147A5D5/"/>
      <tstamp>6158B24E</tstamp>
    </comp>
    <comp ref="R37">
      <value>10k</value>
      <footprint>agg:0603</footprint>
      <fields>
        <field name="Farnell">2447230</field>
        <field name="Voltage">50V</field>
      </fields>
      <libsource lib="agg" part="R" description=""/>
      <sheetpath names="/Boost Converter/" tstamps="/6147A5D5/"/>
      <tstamp>6158B254</tstamp>
    </comp>
    <comp ref="C29">
      <value>100p</value>
      <footprint>agg:0603</footprint>
      <fields>
        <field name="Farnell">9406115</field>
        <field name="Voltage">50V</field>
      </fields>
      <libsource lib="agg" part="C" description=""/>
      <sheetpath names="/Boost Converter/" tstamps="/6147A5D5/"/>
      <tstamp>6158B26F</tstamp>
    </comp>
    <comp ref="IC5">
      <value>NCV8460A</value>
      <footprint>agg:SOIC-8</footprint>
      <datasheet>https://www.onsemi.com/pub/Collateral/NCV8460-D.PDF</datasheet>
      <fields>
        <field name="Farnell">2845252</field>
      </fields>
      <libsource lib="agg" part="NCV8460A" description="Self Protected High Side Driver with Temperature Shutdown and Current Limit"/>
      <sheetpath names="/Boost Converter/" tstamps="/6147A5D5/"/>
      <tstamp>61AD0594</tstamp>
    </comp>
    <comp ref="R27">
      <value>100</value>
      <footprint>agg:D2PAK_R</footprint>
      <fields>
        <field name="Farnell">2101651</field>
      </fields>
      <libsource lib="agg" part="R" description=""/>
      <sheetpath names="/Boost Converter/" tstamps="/6147A5D5/"/>
      <tstamp>614C62BB</tstamp>
    </comp>
    <comp ref="R29">
      <value>100</value>
      <footprint>agg:D2PAK_R</footprint>
      <fields>
        <field name="Farnell">2101651</field>
      </fields>
      <libsource lib="agg" part="R" description=""/>
      <sheetpath names="/Boost Converter/" tstamps="/6147A5D5/"/>
      <tstamp>614C62B5</tstamp>
    </comp>
    <comp ref="R32">
      <value>100</value>
      <footprint>agg:D2PAK_R</footprint>
      <fields>
        <field name="Farnell">2101651</field>
      </fields>
      <libsource lib="agg" part="R" description=""/>
      <sheetpath names="/Boost Converter/" tstamps="/6147A5D5/"/>
      <tstamp>614C62AF</tstamp>
    </comp>
    <comp ref="R38">
      <value>100</value>
      <footprint>agg:D2PAK_R</footprint>
      <fields>
        <field name="Farnell">2101651</field>
      </fields>
      <libsource lib="agg" part="R" description=""/>
      <sheetpath names="/Boost Converter/" tstamps="/6147A5D5/"/>
      <tstamp>614C62A9</tstamp>
    </comp>
    <comp ref="IC11">
      <value>AD8551</value>
      <footprint>agg:MSOP-8</footprint>
      <datasheet>https://www.analog.com/media/en/technical-documentation/data-sheets/AD8551_8552_8554.pdf</datasheet>
      <fields>
        <field name="Farnell">2460985</field>
      </fields>
      <libsource lib="agg" part="AD8551" description="Zero-Drift, Single-Supply, Rail-to-Rail Input/Output Operational Amplifiers"/>
      <sheetpath names="/Boost Converter/" tstamps="/6147A5D5/"/>
      <tstamp>62A25F5F</tstamp>
    </comp>
    <comp ref="IC10">
      <value>AD8551</value>
      <footprint>agg:MSOP-8</footprint>
      <datasheet>https://www.analog.com/media/en/technical-documentation/data-sheets/AD8551_8552_8554.pdf</datasheet>
      <fields>
        <field name="Farnell">2460985</field>
      </fields>
      <libsource lib="agg" part="AD8551" description="Zero-Drift, Single-Supply, Rail-to-Rail Input/Output Operational Amplifiers"/>
      <sheetpath names="/Boost Converter/" tstamps="/6147A5D5/"/>
      <tstamp>62A266A8</tstamp>
    </comp>
    <comp ref="C38">
      <value>100n</value>
      <footprint>agg:0603</footprint>
      <fields>
        <field name="Farnell">2320803</field>
        <field name="Voltage">50V</field>
      </fields>
      <libsource lib="agg" part="C" description=""/>
      <sheetpath names="/Boost Converter/" tstamps="/6147A5D5/"/>
      <tstamp>62A2A0C8</tstamp>
    </comp>
    <comp ref="C39">
      <value>1µ</value>
      <footprint>agg:0603</footprint>
      <fields>
        <field name="Farnell">2320814</field>
        <field name="Voltage">16V</field>
      </fields>
      <libsource lib="agg" part="C" description=""/>
      <sheetpath names="/Boost Converter/" tstamps="/6147A5D5/"/>
      <tstamp>62A2A0D3</tstamp>
    </comp>
    <comp ref="D15">
      <value>STTH512B</value>
      <footprint>agg:DPAK_DIODE</footprint>
      <datasheet>https://www.st.com/resource/en/datasheet/stth512.pdf</datasheet>
      <fields>
        <field name="Farnell">2344055</field>
      </fields>
      <libsource lib="agg" part="SCHOTTKY" description="Schottky Diode"/>
      <sheetpath names="/Boost Converter/" tstamps="/6147A5D5/"/>
      <tstamp>62C4FC38</tstamp>
    </comp>
    <comp ref="Q1">
      <value>STB45N60DM2AG</value>
      <footprint>agg:D2PAK_GDS</footprint>
      <datasheet>https://www.st.com/resource/en/datasheet/stb45n60dm2ag.pdf</datasheet>
      <fields>
        <field name="Farnell">3129762</field>
      </fields>
      <libsource lib="agg" part="NFET_GDS" description="Generic N-channel FET"/>
      <sheetpath names="/Boost Converter/" tstamps="/6147A5D5/"/>
      <tstamp>62C5D73E</tstamp>
    </comp>
    <comp ref="Q2">
      <value>STB45N60DM2AG</value>
      <footprint>agg:D2PAK_GDS</footprint>
      <datasheet>https://www.st.com/resource/en/datasheet/stb45n60dm2ag.pdf</datasheet>
      <fields>
        <field name="Farnell">3129762</field>
      </fields>
      <libsource lib="agg" part="NFET_GDS" description="Generic N-channel FET"/>
      <sheetpath names="/Boost Converter/" tstamps="/6147A5D5/"/>
      <tstamp>62C5E943</tstamp>
    </comp>
    <comp ref="Q3">
      <value>STB45N60DM2AG</value>
      <footprint>agg:D2PAK_GDS</footprint>
      <datasheet>https://www.st.com/resource/en/datasheet/stb45n60dm2ag.pdf</datasheet>
      <fields>
        <field name="Farnell">3129762</field>
      </fields>
      <libsource lib="agg" part="NFET_GDS" description="Generic N-channel FET"/>
      <sheetpath names="/Boost Converter/" tstamps="/6147A5D5/"/>
      <tstamp>62C60334</tstamp>
    </comp>
    <comp ref="L2">
      <value>47µH</value>
      <footprint>agg:MSS1210</footprint>
      <datasheet>http://www.farnell.com/datasheets/1681953.pdf</datasheet>
      <fields>
        <field name="Farnell">2288335</field>
      </fields>
      <libsource lib="agg" part="L" description=""/>
      <sheetpath names="/Boost Converter/" tstamps="/6147A5D5/"/>
      <tstamp>62C978F3</tstamp>
    </comp>
    <comp ref="C24">
      <value>100p</value>
      <footprint>agg:0603</footprint>
      <fields>
        <field name="Farnell">9406115</field>
        <field name="Voltage">50V</field>
      </fields>
      <libsource lib="agg" part="C" description=""/>
      <sheetpath names="/Boost Converter/" tstamps="/6147A5D5/"/>
      <tstamp>6158B2AC</tstamp>
    </comp>
    <comp ref="R25">
      <value>10k</value>
      <footprint>agg:0603</footprint>
      <fields>
        <field name="Farnell">2447230</field>
        <field name="Voltage">50V</field>
      </fields>
      <libsource lib="agg" part="R" description=""/>
      <sheetpath names="/Boost Converter/" tstamps="/6147A5D5/"/>
      <tstamp>6158B296</tstamp>
    </comp>
    <comp ref="R19">
      <value>499k</value>
      <footprint>agg:0805</footprint>
      <fields>
        <field name="Farnell">2447667</field>
        <field name="Voltage">150V</field>
      </fields>
      <libsource lib="agg" part="R" description=""/>
      <sheetpath names="/Boost Converter/" tstamps="/6147A5D5/"/>
      <tstamp>6158B290</tstamp>
    </comp>
    <comp ref="C23">
      <value>68µ</value>
      <footprint>agg:PANASONIC-SMDCAP-K</footprint>
      <datasheet>http://industrial.panasonic.com/cdbs/www-data/pdf/RDE0000/ABA0000C1202.pdf</datasheet>
      <fields>
        <field name="Farnell">2326343</field>
        <field name="Voltage">250V</field>
      </fields>
      <libsource lib="agg" part="CP" description="Polarised Capacitor"/>
      <sheetpath names="/Boost Converter/" tstamps="/6147A5D5/"/>
      <tstamp>62D1EA7B</tstamp>
    </comp>
    <comp ref="C26">
      <value>68µ</value>
      <footprint>agg:PANASONIC-SMDCAP-K</footprint>
      <datasheet>http://industrial.panasonic.com/cdbs/www-data/pdf/RDE0000/ABA0000C1202.pdf</datasheet>
      <fields>
        <field name="Farnell">2326343</field>
        <field name="Voltage">250V</field>
      </fields>
      <libsource lib="agg" part="CP" description="Polarised Capacitor"/>
      <sheetpath names="/Boost Converter/" tstamps="/6147A5D5/"/>
      <tstamp>62D2382F</tstamp>
    </comp>
    <comp ref="C20">
      <value>1µ</value>
      <footprint>agg:2220</footprint>
      <datasheet>http://www.farnell.com/datasheets/2048632.pdf</datasheet>
      <fields>
        <field name="Farnell">1828845</field>
        <field name="Voltage">250V</field>
      </fields>
      <libsource lib="agg" part="C" description=""/>
      <sheetpath names="/Boost Converter/" tstamps="/6147A5D5/"/>
      <tstamp>62DA9FD2</tstamp>
    </comp>
    <comp ref="C25">
      <value>1µ</value>
      <footprint>agg:2220</footprint>
      <datasheet>http://www.farnell.com/datasheets/2048632.pdf</datasheet>
      <fields>
        <field name="Farnell">1828845</field>
        <field name="Voltage">250V</field>
      </fields>
      <libsource lib="agg" part="C" description=""/>
      <sheetpath names="/Boost Converter/" tstamps="/6147A5D5/"/>
      <tstamp>62DADCD4</tstamp>
    </comp>
    <comp ref="C21">
      <value>10µ</value>
      <footprint>agg:1210</footprint>
      <fields>
        <field name="Farnell">2781426</field>
        <field name="Voltage">50V</field>
      </fields>
      <libsource lib="agg" part="C" description=""/>
      <sheetpath names="/Boost Converter/" tstamps="/6147A5D5/"/>
      <tstamp>62E07191</tstamp>
    </comp>
    <comp ref="R51">
      <value>100k</value>
      <footprint>agg:1206</footprint>
      <fields>
        <field name="Farnell">2447453</field>
        <field name="Voltage">200V</field>
      </fields>
      <libsource lib="agg" part="R" description=""/>
      <sheetpath names="/Boost Converter/" tstamps="/6147A5D5/"/>
      <tstamp>62F47BC1</tstamp>
    </comp>
    <comp ref="R52">
      <value>100k</value>
      <footprint>agg:1206</footprint>
      <fields>
        <field name="Farnell">2447453</field>
        <field name="Voltage">200V</field>
      </fields>
      <libsource lib="agg" part="R" description=""/>
      <sheetpath names="/Boost Converter/" tstamps="/6147A5D5/"/>
      <tstamp>62F48466</tstamp>
    </comp>
    <comp ref="R50">
      <value>1k</value>
      <footprint>agg:0603</footprint>
      <fields>
        <field name="Farnell">2447272</field>
        <field name="Voltage">50V</field>
      </fields>
      <libsource lib="agg" part="R" description=""/>
      <sheetpath names="/Boost Converter/" tstamps="/6147A5D5/"/>
      <tstamp>630A0C61</tstamp>
    </comp>
    <comp ref="C15">
      <value>DNF</value>
      <footprint>agg:0805</footprint>
      <fields>
        <field name="Voltage">250V</field>
      </fields>
      <libsource lib="agg" part="C" description=""/>
      <sheetpath names="/Boost Converter/" tstamps="/6147A5D5/"/>
      <tstamp>632CD69D</tstamp>
    </comp>
    <comp ref="R49">
      <value>DNF</value>
      <footprint>agg:0805</footprint>
      <libsource lib="agg" part="R" description=""/>
      <sheetpath names="/Boost Converter/" tstamps="/6147A5D5/"/>
      <tstamp>632EE691</tstamp>
    </comp>
    <comp ref="TP7">
      <value>TESTPAD</value>
      <footprint>agg:SIL-254P-01</footprint>
      <libsource lib="agg" part="TESTPAD" description="Test pad"/>
      <sheetpath names="/Boost Converter/" tstamps="/6147A5D5/"/>
      <tstamp>5D679B14</tstamp>
    </comp>
    <comp ref="TP11">
      <value>TESTPAD</value>
      <footprint>agg:SIL-254P-01</footprint>
      <libsource lib="agg" part="TESTPAD" description="Test pad"/>
      <sheetpath names="/Boost Converter/" tstamps="/6147A5D5/"/>
      <tstamp>5D68B46C</tstamp>
    </comp>
    <comp ref="TP10">
      <value>TESTPAD</value>
      <footprint>agg:TESTPAD</footprint>
      <libsource lib="agg" part="TESTPAD" description="Test pad"/>
      <sheetpath names="/Boost Converter/" tstamps="/6147A5D5/"/>
      <tstamp>5D7276D3</tstamp>
    </comp>
    <comp ref="TP14">
      <value>TESTPAD</value>
      <footprint>agg:TESTPAD</footprint>
      <libsource lib="agg" part="TESTPAD" description="Test pad"/>
      <sheetpath names="/Boost Converter/" tstamps="/6147A5D5/"/>
      <tstamp>5D738EAB</tstamp>
    </comp>
    <comp ref="TP16">
      <value>TESTPAD</value>
      <footprint>agg:TESTPAD</footprint>
      <libsource lib="agg" part="TESTPAD" description="Test pad"/>
      <sheetpath names="/Boost Converter/" tstamps="/6147A5D5/"/>
      <tstamp>5D7583A6</tstamp>
    </comp>
    <comp ref="TP6">
      <value>TESTPAD</value>
      <footprint>agg:TESTPAD</footprint>
      <libsource lib="agg" part="TESTPAD" description="Test pad"/>
      <sheetpath names="/Boost Converter/" tstamps="/6147A5D5/"/>
      <tstamp>5D76F2D7</tstamp>
    </comp>
    <comp ref="TP9">
      <value>TESTPAD</value>
      <footprint>agg:TESTPAD</footprint>
      <libsource lib="agg" part="TESTPAD" description="Test pad"/>
      <sheetpath names="/Boost Converter/" tstamps="/6147A5D5/"/>
      <tstamp>5D795469</tstamp>
    </comp>
    <comp ref="TP13">
      <value>TESTPAD</value>
      <footprint>agg:TESTPAD</footprint>
      <libsource lib="agg" part="TESTPAD" description="Test pad"/>
      <sheetpath names="/Boost Converter/" tstamps="/6147A5D5/"/>
      <tstamp>5D7B9AA9</tstamp>
    </comp>
    <comp ref="TP15">
      <value>TESTPAD</value>
      <footprint>agg:TESTPAD</footprint>
      <libsource lib="agg" part="TESTPAD" description="Test pad"/>
      <sheetpath names="/Boost Converter/" tstamps="/6147A5D5/"/>
      <tstamp>5D7CC406</tstamp>
    </comp>
  </components>
  <libparts>
    <libpart lib="agg" part="AD8551">
      <description>Zero-Drift, Single-Supply, Rail-to-Rail Input/Output Operational Amplifiers</description>
      <docs>https://www.analog.com/media/en/technical-documentation/data-sheets/AD8551_8552_8554.pdf</docs>
      <fields>
        <field name="Reference">IC</field>
        <field name="Value">AD8551</field>
        <field name="Footprint">agg:SOIC-8</field>
        <field name="Farnell">1838869</field>
      </fields>
      <pins>
        <pin num="1" name="~" type="NotConnected"/>
        <pin num="2" name="-" type="input"/>
        <pin num="3" name="+" type="input"/>
        <pin num="4" name="~" type="power_in"/>
        <pin num="5" name="~" type="NotConnected"/>
        <pin num="6" name="~" type="output"/>
        <pin num="7" name="~" type="power_in"/>
        <pin num="8" name="~" type="NotConnected"/>
      </pins>
    </libpart>
    <libpart lib="agg" part="ADP3335">
      <description>LDO Voltage Regulator</description>
      <fields>
        <field name="Reference">IC</field>
        <field name="Value">ADP3335</field>
        <field name="Footprint">agg:MSOP-8</field>
        <field name="Farnell">2067775</field>
      </fields>
      <pins>
        <pin num="1" name="OUT" type="power_out"/>
        <pin num="2" name="OUT" type="passive"/>
        <pin num="3" name="OUT" type="passive"/>
        <pin num="4" name="GND" type="power_in"/>
        <pin num="5" name="NR" type="power_out"/>
        <pin num="6" name="SD" type="input"/>
        <pin num="7" name="IN" type="power_in"/>
        <pin num="8" name="IN" type="power_in"/>
      </pins>
    </libpart>
    <libpart lib="agg" part="BarrelJack">
      <fields>
        <field name="Reference">J</field>
        <field name="Value">BarrelJack</field>
        <field name="Footprint">agg:BARRELJACK</field>
      </fields>
      <pins>
        <pin num="1" name="TIP" type="passive"/>
        <pin num="2" name="SW" type="passive"/>
        <pin num="3" name="RING" type="passive"/>
      </pins>
    </libpart>
    <libpart lib="agg" part="C">
      <fields>
        <field name="Reference">C</field>
        <field name="Value">C</field>
      </fields>
      <pins>
        <pin num="1" name="~" type="passive"/>
        <pin num="2" name="~" type="passive"/>
      </pins>
    </libpart>
    <libpart lib="agg" part="CONN_01x03">
      <fields>
        <field name="Reference">J</field>
        <field name="Value">CONN_01x03</field>
      </fields>
      <pins>
        <pin num="1" name="1" type="passive"/>
        <pin num="2" name="2" type="passive"/>
        <pin num="3" name="3" type="passive"/>
      </pins>
    </libpart>
    <libpart lib="agg" part="CONN_01x04">
      <fields>
        <field name="Reference">J</field>
        <field name="Value">CONN_01x04</field>
      </fields>
      <pins>
        <pin num="1" name="1" type="passive"/>
        <pin num="2" name="2" type="passive"/>
        <pin num="3" name="3" type="passive"/>
        <pin num="4" name="4" type="passive"/>
      </pins>
    </libpart>
    <libpart lib="agg" part="CP">
      <description>Polarised Capacitor</description>
      <fields>
        <field name="Reference">C</field>
        <field name="Value">CP</field>
      </fields>
      <pins>
        <pin num="1" name="~" type="passive"/>
        <pin num="2" name="~" type="passive"/>
      </pins>
    </libpart>
    <libpart lib="agg" part="ESD_DIODE">
      <description>ESD diode</description>
      <fields>
        <field name="Reference">D</field>
        <field name="Value">ESD_DIODE</field>
        <field name="Footprint">agg:0402</field>
        <field name="Farnell">2368169</field>
      </fields>
      <pins>
        <pin num="1" name="1" type="passive"/>
        <pin num="2" name="2" type="passive"/>
      </pins>
    </libpart>
    <libpart lib="agg" part="INA139">
      <description>High-Side Measurement Current Shunt Monitor</description>
      <docs>http://www.ti.com/lit/ds/symlink/ina139.pdf</docs>
      <fields>
        <field name="Reference">IC</field>
        <field name="Value">INA139</field>
        <field name="Footprint">agg:SOT-23-5</field>
        <field name="Datasheet">http://www.ti.com/lit/ds/symlink/ina139.pdf</field>
        <field name="Farnell">1470398</field>
      </fields>
      <pins>
        <pin num="1" name="~" type="output"/>
        <pin num="2" name="~" type="power_in"/>
        <pin num="3" name="+" type="input"/>
        <pin num="4" name="-" type="input"/>
        <pin num="5" name="~" type="power_in"/>
      </pins>
    </libpart>
    <libpart lib="agg" part="L">
      <fields>
        <field name="Reference">L</field>
        <field name="Value">L</field>
      </fields>
      <pins>
        <pin num="1" name="~" type="passive"/>
        <pin num="2" name="~" type="passive"/>
      </pins>
    </libpart>
    <libpart lib="agg" part="LED">
      <fields>
        <field name="Reference">D</field>
        <field name="Value">LED</field>
      </fields>
      <pins>
        <pin num="1" name="~" type="passive"/>
        <pin num="2" name="~" type="passive"/>
      </pins>
    </libpart>
    <libpart lib="agg" part="MCP1416">
      <description>1.5A High Speed Power MOSFET Driver</description>
      <docs>http://ww1.microchip.com/downloads/en/DeviceDoc/20002092F.pdf</docs>
      <fields>
        <field name="Reference">IC</field>
        <field name="Value">MCP1416</field>
        <field name="Footprint">agg:SOT-23-5</field>
        <field name="Datasheet">http://ww1.microchip.com/downloads/en/DeviceDoc/20002092F.pdf</field>
        <field name="Farnell">1630421</field>
      </fields>
      <pins>
        <pin num="1" name="NC" type="NotConnected"/>
        <pin num="2" name="VDD" type="power_in"/>
        <pin num="3" name="IN" type="input"/>
        <pin num="4" name="GND" type="power_in"/>
        <pin num="5" name="OUT" type="output"/>
      </pins>
    </libpart>
    <libpart lib="agg" part="NCV8460A">
      <description>Self Protected High Side Driver with Temperature Shutdown and Current Limit</description>
      <docs>https://www.onsemi.com/pub/Collateral/NCV8460-D.PDF</docs>
      <fields>
        <field name="Reference">IC</field>
        <field name="Value">NCV8460A</field>
        <field name="Footprint">agg:SOIC-8</field>
        <field name="Datasheet">https://www.onsemi.com/pub/Collateral/NCV8460-D.PDF</field>
        <field name="Farnell">2845252</field>
      </fields>
      <pins>
        <pin num="1" name="GND" type="power_in"/>
        <pin num="2" name="IN" type="input"/>
        <pin num="3" name="STAT" type="output"/>
        <pin num="4" name="NC" type="NotConnected"/>
        <pin num="5" name="VD" type="power_in"/>
        <pin num="6" name="OUT" type="power_out"/>
        <pin num="7" name="OUT" type="passive"/>
        <pin num="8" name="VD" type="power_in"/>
      </pins>
    </libpart>
    <libpart lib="agg" part="NFET_GDS">
      <description>Generic N-channel FET</description>
      <fields>
        <field name="Reference">Q</field>
        <field name="Value">NFET_GDS</field>
      </fields>
      <pins>
        <pin num="D" name="D" type="passive"/>
        <pin num="G" name="G" type="passive"/>
        <pin num="S" name="S" type="passive"/>
      </pins>
    </libpart>
    <libpart lib="agg" part="PART">
      <description>Generic placeholder part</description>
      <fields>
        <field name="Reference">X</field>
        <field name="Value">PART</field>
      </fields>
    </libpart>
    <libpart lib="agg" part="R">
      <fields>
        <field name="Reference">R</field>
        <field name="Value">R</field>
      </fields>
      <pins>
        <pin num="1" name="~" type="passive"/>
        <pin num="2" name="~" type="passive"/>
      </pins>
    </libpart>
    <libpart lib="agg" part="SCHOTTKY">
      <description>Schottky Diode</description>
      <fields>
        <field name="Reference">D</field>
        <field name="Value">SCHOTTKY</field>
      </fields>
      <pins>
        <pin num="1" name="~" type="passive"/>
        <pin num="2" name="~" type="passive"/>
      </pins>
    </libpart>
    <libpart lib="agg" part="STM32F3xxKxTx">
      <description>STM32F3 32 pin LQFP package</description>
      <docs>http://www.st.com/resource/en/datasheet/stm32f334k8.pdf</docs>
      <fields>
        <field name="Reference">IC</field>
        <field name="Value">STM32F3xxKxTx</field>
        <field name="Footprint">agg:LQFP-32</field>
        <field name="Datasheet">http://www.st.com/resource/en/datasheet/stm32f334k8.pdf</field>
        <field name="Farnell">2469571</field>
      </fields>
      <pins>
        <pin num="1" name="VDD" type="power_in"/>
        <pin num="2" name="PF0" type="BiDi"/>
        <pin num="3" name="PF1" type="BiDi"/>
        <pin num="4" name="NRST" type="input"/>
        <pin num="5" name="VDDA" type="power_in"/>
        <pin num="6" name="PA0" type="BiDi"/>
        <pin num="7" name="PA1" type="BiDi"/>
        <pin num="8" name="PA2" type="BiDi"/>
        <pin num="9" name="PA3" type="BiDi"/>
        <pin num="10" name="PA4" type="BiDi"/>
        <pin num="11" name="PA5" type="BiDi"/>
        <pin num="12" name="PA6" type="BiDi"/>
        <pin num="13" name="PA7" type="BiDi"/>
        <pin num="14" name="PB0" type="BiDi"/>
        <pin num="15" name="PB1" type="BiDi"/>
        <pin num="16" name="VSS" type="power_in"/>
        <pin num="17" name="VDD" type="power_in"/>
        <pin num="18" name="PA8" type="BiDi"/>
        <pin num="19" name="PA9" type="BiDi"/>
        <pin num="20" name="PA10" type="BiDi"/>
        <pin num="21" name="PA11" type="BiDi"/>
        <pin num="22" name="PA12" type="BiDi"/>
        <pin num="23" name="PA13" type="BiDi"/>
        <pin num="24" name="PA14" type="BiDi"/>
        <pin num="25" name="PA15" type="BiDi"/>
        <pin num="26" name="PB3" type="BiDi"/>
        <pin num="27" name="PB4" type="BiDi"/>
        <pin num="28" name="PB5" type="BiDi"/>
        <pin num="29" name="PB6" type="BiDi"/>
        <pin num="30" name="PB7" type="BiDi"/>
        <pin num="31" name="BOOT0" type="input"/>
        <pin num="32" name="VSS" type="power_in"/>
      </pins>
    </libpart>
    <libpart lib="agg" part="SWD">
      <description>Serial Wire Debug Port</description>
      <fields>
        <field name="Reference">P</field>
        <field name="Value">SWD</field>
        <field name="Footprint">agg:FTSH-105-01-F-D-K</field>
        <field name="Toby">FTSH-105-01-F-D-K</field>
      </fields>
      <pins>
        <pin num="1" name="VTref" type="power_in"/>
        <pin num="2" name="SWDIO/TMS" type="BiDi"/>
        <pin num="3" name="GND" type="power_in"/>
        <pin num="4" name="SWDCLK/TCK" type="BiDi"/>
        <pin num="5" name="GND" type="power_in"/>
        <pin num="6" name="SWO/TDO" type="BiDi"/>
        <pin num="7" name="KEY" type="NotConnected"/>
        <pin num="8" name="TDI" type="BiDi"/>
        <pin num="9" name="GND" type="power_in"/>
        <pin num="10" name="nRESET" type="openCol"/>
      </pins>
    </libpart>
    <libpart lib="agg" part="TCXO_ST">
      <description>4 pin TCXO with Standy</description>
      <fields>
        <field name="Reference">Y</field>
        <field name="Value">TCXO_ST</field>
        <field name="Farnell">2405760</field>
      </fields>
      <pins>
        <pin num="1" name="~ST" type="input"/>
        <pin num="2" name="GND" type="power_in"/>
        <pin num="3" name="OUT" type="output"/>
        <pin num="4" name="VCC" type="power_in"/>
      </pins>
    </libpart>
    <libpart lib="agg" part="TESTPAD">
      <description>Test pad</description>
      <fields>
        <field name="Reference">TP</field>
        <field name="Value">TESTPAD</field>
        <field name="Footprint">agg:TESTPAD</field>
      </fields>
      <pins>
        <pin num="1" name="TP" type="input"/>
      </pins>
    </libpart>
    <libpart lib="agg" part="TSR1">
      <description>TSR1 Switch Mode Regulators</description>
      <docs>http://www.tracopower.com/products/tsr1.pdf</docs>
      <fields>
        <field name="Reference">IC</field>
        <field name="Value">TSR1</field>
        <field name="Footprint">agg:TSR1</field>
        <field name="Datasheet">http://www.tracopower.com/products/tsr1.pdf</field>
      </fields>
      <pins>
        <pin num="1" name="VIN" type="power_in"/>
        <pin num="2" name="GND" type="power_in"/>
        <pin num="3" name="VOUT" type="power_out"/>
      </pins>
    </libpart>
  </libparts>
  <libraries>
    <library logical="agg">
      <uri>/home/adam/Projects/iggie/psu/../agg-kicad/agg-kicad.lib</uri>
    </library>
  </libraries>
  <nets>
    <net code="1" name="3v3">
      <node ref="C6" pin="2"/>
      <node ref="C45" pin="1"/>
      <node ref="IC9" pin="5"/>
      <node ref="C40" pin="1"/>
      <node ref="R5" pin="1"/>
      <node ref="TP5" pin="1"/>
      <node ref="IC4" pin="1"/>
      <node ref="IC11" pin="7"/>
      <node ref="C39" pin="1"/>
      <node ref="C38" pin="1"/>
      <node ref="IC10" pin="7"/>
      <node ref="C46" pin="1"/>
      <node ref="C41" pin="1"/>
      <node ref="IC4" pin="17"/>
      <node ref="L3" pin="2"/>
      <node ref="P1" pin="1"/>
      <node ref="Y1" pin="1"/>
      <node ref="C13" pin="1"/>
      <node ref="Y1" pin="4"/>
      <node ref="C36" pin="1"/>
      <node ref="C5" pin="1"/>
      <node ref="C37" pin="1"/>
      <node ref="C8" pin="1"/>
      <node ref="C9" pin="1"/>
      <node ref="C10" pin="1"/>
      <node ref="IC1" pin="1"/>
      <node ref="IC1" pin="2"/>
      <node ref="IC1" pin="3"/>
      <node ref="R7" pin="2"/>
      <node ref="IC12" pin="7"/>
    </net>
    <net code="2" name="/LED_OK2">
      <node ref="R13" pin="1"/>
      <node ref="IC4" pin="28"/>
    </net>
    <net code="3" name="/LED_OK1">
      <node ref="R12" pin="1"/>
      <node ref="IC4" pin="27"/>
    </net>
    <net code="4" name="/LED_STAT">
      <node ref="R11" pin="1"/>
      <node ref="IC4" pin="26"/>
    </net>
    <net code="5" name="/GD2">
      <node ref="IC4" pin="20"/>
      <node ref="TP11" pin="1"/>
      <node ref="IC7" pin="3"/>
      <node ref="IC4" pin="15"/>
    </net>
    <net code="6" name="Net-(D10-Pad2)">
      <node ref="D10" pin="2"/>
      <node ref="R10" pin="2"/>
    </net>
    <net code="7" name="Net-(D13-Pad2)">
      <node ref="R13" pin="2"/>
      <node ref="D13" pin="2"/>
    </net>
    <net code="8" name="Net-(D12-Pad2)">
      <node ref="R12" pin="2"/>
      <node ref="D12" pin="2"/>
    </net>
    <net code="9" name="Net-(D11-Pad2)">
      <node ref="R11" pin="2"/>
      <node ref="D11" pin="2"/>
    </net>
    <net code="10" name="24v">
      <node ref="R6" pin="1"/>
      <node ref="C1" pin="2"/>
      <node ref="IC2" pin="1"/>
      <node ref="IC5" pin="8"/>
      <node ref="J3" pin="1"/>
      <node ref="IC5" pin="5"/>
      <node ref="R1" pin="1"/>
      <node ref="D1" pin="1"/>
      <node ref="TP1" pin="1"/>
      <node ref="D9" pin="1"/>
      <node ref="IC3" pin="1"/>
      <node ref="C2" pin="1"/>
      <node ref="C3" pin="1"/>
    </net>
    <net code="11" name="GND">
      <node ref="C40" pin="2"/>
      <node ref="IC9" pin="2"/>
      <node ref="R22" pin="2"/>
      <node ref="C34" pin="2"/>
      <node ref="C37" pin="2"/>
      <node ref="C36" pin="2"/>
      <node ref="C35" pin="2"/>
      <node ref="C13" pin="2"/>
      <node ref="Y1" pin="2"/>
      <node ref="R39" pin="2"/>
      <node ref="C29" pin="2"/>
      <node ref="R37" pin="2"/>
      <node ref="C9" pin="2"/>
      <node ref="IC5" pin="1"/>
      <node ref="C8" pin="2"/>
      <node ref="C10" pin="2"/>
      <node ref="C12" pin="2"/>
      <node ref="C11" pin="2"/>
      <node ref="C19" pin="2"/>
      <node ref="C14" pin="2"/>
      <node ref="C31" pin="2"/>
      <node ref="IC7" pin="4"/>
      <node ref="C18" pin="2"/>
      <node ref="C22" pin="1"/>
      <node ref="C27" pin="2"/>
      <node ref="C28" pin="2"/>
      <node ref="R35" pin="2"/>
      <node ref="R33" pin="2"/>
      <node ref="R36" pin="2"/>
      <node ref="R34" pin="2"/>
      <node ref="C33" pin="2"/>
      <node ref="C32" pin="2"/>
      <node ref="IC6" pin="4"/>
      <node ref="C30" pin="2"/>
      <node ref="IC12" pin="4"/>
      <node ref="C45" pin="2"/>
      <node ref="R45" pin="2"/>
      <node ref="R48" pin="2"/>
      <node ref="R40" pin="2"/>
      <node ref="IC8" pin="4"/>
      <node ref="C46" pin="2"/>
      <node ref="R47" pin="2"/>
      <node ref="C47" pin="2"/>
      <node ref="C41" pin="2"/>
      <node ref="IC11" pin="4"/>
      <node ref="C24" pin="2"/>
      <node ref="R25" pin="2"/>
      <node ref="Q3" pin="S"/>
      <node ref="C26" pin="1"/>
      <node ref="C15" pin="2"/>
      <node ref="C25" pin="2"/>
      <node ref="C21" pin="2"/>
      <node ref="R52" pin="2"/>
      <node ref="R46" pin="2"/>
      <node ref="C38" pin="2"/>
      <node ref="C39" pin="2"/>
      <node ref="IC10" pin="4"/>
      <node ref="D9" pin="2"/>
      <node ref="D11" pin="1"/>
      <node ref="D4" pin="1"/>
      <node ref="C1" pin="1"/>
      <node ref="C3" pin="2"/>
      <node ref="C5" pin="2"/>
      <node ref="C2" pin="2"/>
      <node ref="D2" pin="2"/>
      <node ref="J3" pin="4"/>
      <node ref="D13" pin="1"/>
      <node ref="D12" pin="1"/>
      <node ref="IC4" pin="31"/>
      <node ref="IC4" pin="32"/>
      <node ref="IC4" pin="16"/>
      <node ref="D5" pin="1"/>
      <node ref="R2" pin="2"/>
      <node ref="D3" pin="1"/>
      <node ref="D6" pin="1"/>
      <node ref="D10" pin="1"/>
      <node ref="C4" pin="2"/>
      <node ref="C7" pin="2"/>
      <node ref="P1" pin="9"/>
      <node ref="IC3" pin="2"/>
      <node ref="IC2" pin="2"/>
      <node ref="P1" pin="5"/>
      <node ref="J2" pin="3"/>
      <node ref="P1" pin="3"/>
      <node ref="TP2" pin="1"/>
      <node ref="D8" pin="2"/>
      <node ref="IC1" pin="4"/>
      <node ref="D7" pin="2"/>
    </net>
    <net code="12" name="/24VEN">
      <node ref="IC5" pin="2"/>
      <node ref="R22" pin="1"/>
      <node ref="IC4" pin="21"/>
    </net>
    <net code="13" name="Net-(D1-Pad2)">
      <node ref="D1" pin="2"/>
      <node ref="J2" pin="1"/>
      <node ref="D2" pin="1"/>
    </net>
    <net code="14" name="Net-(D4-Pad2)">
      <node ref="D4" pin="2"/>
      <node ref="R4" pin="2"/>
    </net>
    <net code="15" name="5v">
      <node ref="IC1" pin="7"/>
      <node ref="IC1" pin="8"/>
      <node ref="TP4" pin="1"/>
      <node ref="C4" pin="1"/>
      <node ref="IC1" pin="6"/>
      <node ref="IC3" pin="3"/>
      <node ref="R4" pin="1"/>
    </net>
    <net code="16" name="Net-(D5-Pad2)">
      <node ref="R5" pin="2"/>
      <node ref="D5" pin="2"/>
    </net>
    <net code="17" name="/100V_MON">
      <node ref="R25" pin="1"/>
      <node ref="IC4" pin="7"/>
      <node ref="TP10" pin="1"/>
      <node ref="R19" pin="2"/>
      <node ref="C24" pin="1"/>
    </net>
    <net code="18" name="/I_24V">
      <node ref="TP6" pin="1"/>
      <node ref="C47" pin="1"/>
      <node ref="IC4" pin="9"/>
      <node ref="R48" pin="1"/>
      <node ref="IC9" pin="1"/>
    </net>
    <net code="19" name="/I_L1">
      <node ref="IC4" pin="13"/>
      <node ref="IC10" pin="6"/>
      <node ref="R41" pin="2"/>
      <node ref="TP9" pin="1"/>
      <node ref="C42" pin="2"/>
    </net>
    <net code="20" name="/I_L2">
      <node ref="IC11" pin="6"/>
      <node ref="TP13" pin="1"/>
      <node ref="IC4" pin="14"/>
      <node ref="R42" pin="2"/>
      <node ref="C43" pin="2"/>
      <node ref="IC4" pin="12"/>
    </net>
    <net code="21" name="/I_400V">
      <node ref="R43" pin="2"/>
      <node ref="IC4" pin="11"/>
      <node ref="C44" pin="2"/>
      <node ref="IC12" pin="6"/>
      <node ref="TP15" pin="1"/>
    </net>
    <net code="22" name="/400V_MON">
      <node ref="R28" pin="2"/>
      <node ref="TP14" pin="1"/>
      <node ref="R37" pin="1"/>
      <node ref="IC4" pin="8"/>
      <node ref="C29" pin="1"/>
    </net>
    <net code="23" name="/GD1">
      <node ref="IC4" pin="18"/>
      <node ref="IC6" pin="3"/>
      <node ref="TP7" pin="1"/>
    </net>
    <net code="24" name="/GD3">
      <node ref="IC8" pin="3"/>
      <node ref="IC4" pin="19"/>
    </net>
    <net code="25" name="/24V_MON">
      <node ref="R2" pin="1"/>
      <node ref="C7" pin="1"/>
      <node ref="R1" pin="2"/>
      <node ref="IC4" pin="6"/>
    </net>
    <net code="26" name="Net-(J1-Pad2)">
      <node ref="J1" pin="2"/>
    </net>
    <net code="27" name="/Boost Converter/HV+">
      <node ref="R21" pin="1"/>
      <node ref="C23" pin="2"/>
      <node ref="D15" pin="1"/>
      <node ref="C20" pin="1"/>
      <node ref="R20" pin="1"/>
      <node ref="R27" pin="1"/>
      <node ref="J1" pin="1"/>
    </net>
    <net code="28" name="/Boost Converter/HV-">
      <node ref="R39" pin="1"/>
      <node ref="R50" pin="2"/>
      <node ref="J1" pin="3"/>
      <node ref="TP16" pin="1"/>
    </net>
    <net code="29" name="15v">
      <node ref="C30" pin="1"/>
      <node ref="IC6" pin="2"/>
      <node ref="C32" pin="1"/>
      <node ref="C34" pin="1"/>
      <node ref="IC2" pin="3"/>
      <node ref="IC7" pin="2"/>
      <node ref="R3" pin="1"/>
      <node ref="TP3" pin="1"/>
      <node ref="C35" pin="1"/>
      <node ref="C33" pin="1"/>
      <node ref="C31" pin="1"/>
      <node ref="IC8" pin="2"/>
    </net>
    <net code="30" name="Net-(J2-Pad2)">
      <node ref="J2" pin="2"/>
    </net>
    <net code="31" name="Net-(D3-Pad2)">
      <node ref="R3" pin="2"/>
      <node ref="D3" pin="2"/>
    </net>
    <net code="32" name="Net-(D6-Pad2)">
      <node ref="D6" pin="2"/>
      <node ref="R6" pin="2"/>
    </net>
    <net code="33" name="Net-(IC4-Pad10)">
      <node ref="IC4" pin="10"/>
    </net>
    <net code="34" name="Net-(IC4-Pad22)">
      <node ref="IC4" pin="22"/>
    </net>
    <net code="35" name="Net-(C6-Pad1)">
      <node ref="IC1" pin="5"/>
      <node ref="C6" pin="1"/>
    </net>
    <net code="36" name="/~RUN">
      <node ref="R7" pin="1"/>
      <node ref="R8" pin="2"/>
      <node ref="IC4" pin="25"/>
    </net>
    <net code="37" name="/SWDIO">
      <node ref="IC4" pin="23"/>
      <node ref="P1" pin="2"/>
    </net>
    <net code="38" name="/SWCLK">
      <node ref="IC4" pin="24"/>
      <node ref="P1" pin="4"/>
    </net>
    <net code="39" name="/LED_FAULT">
      <node ref="R10" pin="1"/>
      <node ref="IC4" pin="30"/>
    </net>
    <net code="40" name="Net-(IC4-Pad2)">
      <node ref="Y1" pin="3"/>
      <node ref="IC4" pin="2"/>
    </net>
    <net code="41" name="Net-(IC4-Pad3)">
      <node ref="IC4" pin="3"/>
    </net>
    <net code="42" name="Net-(P1-Pad7)">
      <node ref="P1" pin="7"/>
    </net>
    <net code="43" name="Net-(P1-Pad8)">
      <node ref="P1" pin="8"/>
    </net>
    <net code="44" name="/~RST">
      <node ref="IC4" pin="4"/>
      <node ref="P1" pin="10"/>
    </net>
    <net code="45" name="Net-(P1-Pad6)">
      <node ref="P1" pin="6"/>
    </net>
    <net code="46" name="Net-(D8-Pad1)">
      <node ref="R8" pin="1"/>
      <node ref="J3" pin="2"/>
      <node ref="D8" pin="1"/>
    </net>
    <net code="47" name="/UART_TX">
      <node ref="IC4" pin="29"/>
      <node ref="R9" pin="2"/>
    </net>
    <net code="48" name="Net-(D7-Pad1)">
      <node ref="R9" pin="1"/>
      <node ref="J3" pin="3"/>
      <node ref="D7" pin="1"/>
    </net>
    <net code="49" name="Net-(C11-Pad1)">
      <node ref="IC4" pin="5"/>
      <node ref="C12" pin="1"/>
      <node ref="C11" pin="1"/>
      <node ref="L3" pin="1"/>
    </net>
    <net code="50" name="Net-(R26-Pad2)">
      <node ref="R26" pin="2"/>
      <node ref="R28" pin="1"/>
    </net>
    <net code="51" name="Net-(R20-Pad2)">
      <node ref="R20" pin="2"/>
      <node ref="R23" pin="1"/>
    </net>
    <net code="52" name="Net-(R23-Pad2)">
      <node ref="R23" pin="2"/>
      <node ref="R26" pin="1"/>
    </net>
    <net code="53" name="Net-(R29-Pad2)">
      <node ref="R29" pin="2"/>
      <node ref="R32" pin="1"/>
    </net>
    <net code="54" name="Net-(R32-Pad2)">
      <node ref="R38" pin="1"/>
      <node ref="R32" pin="2"/>
    </net>
    <net code="55" name="Net-(R27-Pad2)">
      <node ref="R27" pin="2"/>
      <node ref="R29" pin="1"/>
    </net>
    <net code="56" name="Net-(Q3-PadD)">
      <node ref="Q3" pin="D"/>
      <node ref="R38" pin="2"/>
    </net>
    <net code="57" name="/Boost Converter/24VRS+">
      <node ref="R18" pin="1"/>
      <node ref="IC9" pin="3"/>
      <node ref="IC5" pin="7"/>
      <node ref="IC5" pin="6"/>
    </net>
    <net code="58" name="Net-(IC5-Pad3)">
      <node ref="IC5" pin="3"/>
    </net>
    <net code="59" name="Net-(IC5-Pad4)">
      <node ref="IC5" pin="4"/>
    </net>
    <net code="60" name="Net-(C44-Pad1)">
      <node ref="IC12" pin="2"/>
      <node ref="R47" pin="1"/>
      <node ref="R43" pin="1"/>
      <node ref="C44" pin="1"/>
    </net>
    <net code="61" name="Net-(R51-Pad2)">
      <node ref="R52" pin="1"/>
      <node ref="R51" pin="2"/>
    </net>
    <net code="62" name="Net-(C42-Pad1)">
      <node ref="IC10" pin="2"/>
      <node ref="R41" pin="1"/>
      <node ref="C42" pin="1"/>
      <node ref="R45" pin="1"/>
    </net>
    <net code="63" name="Net-(C14-Pad1)">
      <node ref="C14" pin="1"/>
      <node ref="R14" pin="2"/>
    </net>
    <net code="64" name="Net-(C15-Pad1)">
      <node ref="C15" pin="1"/>
      <node ref="C17" pin="2"/>
    </net>
    <net code="65" name="Net-(C16-Pad1)">
      <node ref="C16" pin="1"/>
      <node ref="R49" pin="2"/>
    </net>
    <net code="66" name="Net-(C23-Pad1)">
      <node ref="C23" pin="1"/>
      <node ref="C26" pin="2"/>
    </net>
    <net code="67" name="Net-(C20-Pad2)">
      <node ref="C20" pin="2"/>
      <node ref="C25" pin="1"/>
    </net>
    <net code="68" name="Net-(R24-Pad2)">
      <node ref="R24" pin="2"/>
      <node ref="R51" pin="1"/>
    </net>
    <net code="69" name="/Boost Converter/VRS3">
      <node ref="IC12" pin="3"/>
      <node ref="R50" pin="1"/>
    </net>
    <net code="70" name="Net-(IC10-Pad5)">
      <node ref="IC10" pin="5"/>
    </net>
    <net code="71" name="Net-(IC10-Pad8)">
      <node ref="IC10" pin="8"/>
    </net>
    <net code="72" name="Net-(IC11-Pad1)">
      <node ref="IC11" pin="1"/>
    </net>
    <net code="73" name="Net-(IC11-Pad5)">
      <node ref="IC11" pin="5"/>
    </net>
    <net code="74" name="Net-(IC11-Pad8)">
      <node ref="IC11" pin="8"/>
    </net>
    <net code="75" name="Net-(IC10-Pad1)">
      <node ref="IC10" pin="1"/>
    </net>
    <net code="76" name="Net-(Q1-PadS)">
      <node ref="Q1" pin="S"/>
      <node ref="R34" pin="1"/>
      <node ref="R30" pin="2"/>
    </net>
    <net code="77" name="/Boost Converter/24VRS-">
      <node ref="R18" pin="2"/>
      <node ref="IC9" pin="4"/>
      <node ref="C18" pin="1"/>
      <node ref="C21" pin="1"/>
      <node ref="L1" pin="1"/>
    </net>
    <net code="78" name="/Boost Converter/VRS1">
      <node ref="IC10" pin="3"/>
      <node ref="R30" pin="1"/>
      <node ref="TP8" pin="1"/>
      <node ref="C27" pin="1"/>
    </net>
    <net code="79" name="Net-(C16-Pad2)">
      <node ref="C16" pin="2"/>
      <node ref="C17" pin="1"/>
    </net>
    <net code="80" name="Net-(D14-Pad2)">
      <node ref="L1" pin="2"/>
      <node ref="Q1" pin="D"/>
      <node ref="D14" pin="2"/>
      <node ref="R14" pin="1"/>
    </net>
    <net code="81" name="Net-(R16-Pad2)">
      <node ref="R17" pin="1"/>
      <node ref="R16" pin="2"/>
    </net>
    <net code="82" name="Net-(R17-Pad2)">
      <node ref="R17" pin="2"/>
      <node ref="R49" pin="1"/>
    </net>
    <net code="83" name="Net-(D15-Pad2)">
      <node ref="L2" pin="2"/>
      <node ref="R16" pin="1"/>
      <node ref="D15" pin="2"/>
      <node ref="Q2" pin="D"/>
    </net>
    <net code="84" name="Net-(R21-Pad2)">
      <node ref="R24" pin="1"/>
      <node ref="R21" pin="2"/>
    </net>
    <net code="85" name="Net-(C19-Pad1)">
      <node ref="R19" pin="1"/>
      <node ref="C19" pin="1"/>
      <node ref="L2" pin="1"/>
      <node ref="C22" pin="2"/>
      <node ref="D14" pin="1"/>
    </net>
    <net code="86" name="Net-(IC7-Pad1)">
      <node ref="IC7" pin="1"/>
    </net>
    <net code="87" name="Net-(IC7-Pad5)">
      <node ref="IC7" pin="5"/>
      <node ref="Q2" pin="G"/>
      <node ref="R35" pin="1"/>
    </net>
    <net code="88" name="Net-(IC6-Pad1)">
      <node ref="IC6" pin="1"/>
    </net>
    <net code="89" name="Net-(Q2-PadS)">
      <node ref="Q2" pin="S"/>
      <node ref="R31" pin="2"/>
      <node ref="R36" pin="1"/>
    </net>
    <net code="90" name="/Boost Converter/VRS2">
      <node ref="IC11" pin="3"/>
      <node ref="C28" pin="1"/>
      <node ref="TP12" pin="1"/>
      <node ref="R31" pin="1"/>
    </net>
    <net code="91" name="Net-(IC6-Pad5)">
      <node ref="Q1" pin="G"/>
      <node ref="IC6" pin="5"/>
      <node ref="R33" pin="1"/>
    </net>
    <net code="92" name="Net-(C43-Pad1)">
      <node ref="C43" pin="1"/>
      <node ref="R42" pin="1"/>
      <node ref="R46" pin="1"/>
      <node ref="IC11" pin="2"/>
    </net>
    <net code="93" name="Net-(IC12-Pad1)">
      <node ref="IC12" pin="1"/>
    </net>
    <net code="94" name="Net-(IC12-Pad5)">
      <node ref="IC12" pin="5"/>
    </net>
    <net code="95" name="Net-(IC12-Pad8)">
      <node ref="IC12" pin="8"/>
    </net>
    <net code="96" name="Net-(IC8-Pad1)">
      <node ref="IC8" pin="1"/>
    </net>
    <net code="97" name="Net-(IC8-Pad5)">
      <node ref="Q3" pin="G"/>
      <node ref="IC8" pin="5"/>
      <node ref="R40" pin="1"/>
    </net>
  </nets>
</export>
